{"data":{"results":[{"id":"c1a35315","json":null,"name":"Lifetime","identifier":"lifetime","default":false,"experiment_id":null,"experiment_name":null,"from_paywall":null,"variation_identifier":null,"variation_name":null,"items_v2":[{"id":"f7d92792","name":"Lifetime","product_id":"com.iosmirror.lifetime","store":"app_store"},{"id":"06c48ef5","name":"Annual","product_id":"com.iosmirror.annual","store":"app_store"},{"id":"12b11552","name":"Monthly","product_id":"com.iosmirror.monthly","store":"app_store"}],"items":[{"id":"f7d92792","name":"Lifetime","product_id":"com.iosmirror.lifetime","store":"app_store"},{"id":"06c48ef5","name":"Annual","product_id":"com.iosmirror.annual","store":"app_store"},{"id":"12b11552","name":"Monthly","product_id":"com.iosmirror.monthly","store":"app_store"}]},{"id":"0b37182c","json":null,"name":"Limited Lifetime","identifier":"limited_lifetime","default":false,"experiment_id":null,"experiment_name":null,"from_paywall":null,"variation_identifier":null,"variation_name":null,"items_v2":[{"id":"5ba1b3ae","name":"Plus","product_id":"com.iosmirror.plus","store":"app_store"},{"id":"f7d92792","name":"Lifetime","product_id":"com.iosmirror.lifetime","store":"app_store"}],"items":[{"id":"5ba1b3ae","name":"Plus","product_id":"com.iosmirror.plus","store":"app_store"},{"id":"f7d92792","name":"Lifetime","product_id":"com.iosmirror.lifetime","store":"app_store"}]},{"id":"7f5f6593","json":null,"name":"Limited Annual","identifier":"limited_annual","default":false,"experiment_id":null,"experiment_name":null,"from_paywall":null,"variation_identifier":null,"variation_name":null,"items_v2":[{"id":"06c48ef5","name":"Annual","product_id":"com.iosmirror.annual","store":"app_store"},{"id":"d663e510","name":"Annual Referral","product_id":"com.iosmirror.annual.referral","store":"app_store"}],"items":[{"id":"06c48ef5","name":"Annual","product_id":"com.iosmirror.annual","store":"app_store"},{"id":"d663e510","name":"Annual Referral","product_id":"com.iosmirror.annual.referral","store":"app_store"}]},{"id":"0c15c05e","json":null,"name":"More Options Video","identifier":"moreOptionsVideo","default":false,"experiment_id":null,"experiment_name":null,"from_paywall":null,"variation_identifier":null,"variation_name":null,"items_v2":[{"id":"06c48ef5","name":"Annual","product_id":"com.iosmirror.annual","store":"app_store"},{"id":"12b11552","name":"Monthly","product_id":"com.iosmirror.monthly","store":"app_store"},{"id":"6ca509d0","name":"Weekly","product_id":"com.iosmirror.weekly","store":"app_store"}],"items":[{"id":"06c48ef5","name":"Annual","product_id":"com.iosmirror.annual","store":"app_store"},{"id":"12b11552","name":"Monthly","product_id":"com.iosmirror.monthly","store":"app_store"},{"id":"6ca509d0","name":"Weekly","product_id":"com.iosmirror.weekly","store":"app_store"}]},{"id":"53aebe9e","json":null,"name":"moreOptionsVideoHigh","identifier":"moreOptionsVideoHigh","default":false,"experiment_id":null,"experiment_name":null,"from_paywall":null,"variation_identifier":null,"variation_name":null,"items_v2":[{"id":"b522d301","name":"Annual 1.5","product_id":"com.iosmirror.annual_1_5","store":"app_store"},{"id":"16b55cb5","name":"Monthly 1.5","product_id":"com.iosmirror.monthly_1_5","store":"app_store"},{"id":"f7544ae7","name":"Weekly 1.5","product_id":"com.iosmirror.weekly_1_5","store":"app_store"}],"items":[{"id":"b522d301","name":"Annual 1.5","product_id":"com.iosmirror.annual_1_5","store":"app_store"},{"id":"16b55cb5","name":"Monthly 1.5","product_id":"com.iosmirror.monthly_1_5","store":"app_store"},{"id":"f7544ae7","name":"Weekly 1.5","product_id":"com.iosmirror.weekly_1_5","store":"app_store"}]},{"id":"aecd1ac2","json":null,"name":"moreOptionsLifetime","identifier":"moreOptionsLifetime","default":false,"experiment_id":null,"experiment_name":null,"from_paywall":null,"variation_identifier":null,"variation_name":null,"items_v2":[{"id":"06c48ef5","name":"Annual","product_id":"com.iosmirror.annual","store":"app_store"},{"id":"f7d92792","name":"Lifetime","product_id":"com.iosmirror.lifetime","store":"app_store"},{"id":"12b11552","name":"Monthly","product_id":"com.iosmirror.monthly","store":"app_store"}],"items":[{"id":"06c48ef5","name":"Annual","product_id":"com.iosmirror.annual","store":"app_store"},{"id":"f7d92792","name":"Lifetime","product_id":"com.iosmirror.lifetime","store":"app_store"},{"id":"12b11552","name":"Monthly","product_id":"com.iosmirror.monthly","store":"app_store"}]},{"id":"e49632e0","json":null,"name":"moreOptionsYearMonth","identifier":"moreOptionsYearMonth","default":false,"experiment_id":null,"experiment_name":null,"from_paywall":null,"variation_identifier":null,"variation_name":null,"items_v2":[{"id":"06c48ef5","name":"Annual","product_id":"com.iosmirror.annual","store":"app_store"},{"id":"12b11552","name":"Monthly","product_id":"com.iosmirror.monthly","store":"app_store"}],"items":[{"id":"06c48ef5","name":"Annual","product_id":"com.iosmirror.annual","store":"app_store"},{"id":"12b11552","name":"Monthly","product_id":"com.iosmirror.monthly","store":"app_store"}]},{"id":"28f22f2c","json":null,"name":"enableFreeTrial","identifier":"enableFreeTrial","default":false,"experiment_id":null,"experiment_name":null,"from_paywall":null,"variation_identifier":null,"variation_name":null,"items_v2":[{"id":"99b0f965","name":"Annual Without Trial","product_id":"com.iosmirror.annual_0_5","store":"app_store"},{"id":"06c48ef5","name":"Annual","product_id":"com.iosmirror.annual","store":"app_store"}],"items":[{"id":"99b0f965","name":"Annual Without Trial","product_id":"com.iosmirror.annual_0_5","store":"app_store"},{"id":"06c48ef5","name":"Annual","product_id":"com.iosmirror.annual","store":"app_store"}]},{"id":"85c0d8f5","json":null,"name":"Legacy Upgrade","identifier":"legacy_upgrade","default":false,"experiment_id":null,"experiment_name":null,"from_paywall":null,"variation_identifier":null,"variation_name":null,"items_v2":[{"id":"b522d301","name":"Annual 1.5","product_id":"com.iosmirror.annual_1_5","store":"app_store"},{"id":"f7d92792","name":"Lifetime","product_id":"com.iosmirror.lifetime","store":"app_store"}],"items":[{"id":"b522d301","name":"Annual 1.5","product_id":"com.iosmirror.annual_1_5","store":"app_store"},{"id":"f7d92792","name":"Lifetime","product_id":"com.iosmirror.lifetime","store":"app_store"}]},{"id":"28e2b517","json":null,"name":"referral","identifier":"referral","default":false,"experiment_id":null,"experiment_name":null,"from_paywall":null,"variation_identifier":null,"variation_name":null,"items_v2":[{"id":"d663e510","name":"Annual Referral","product_id":"com.iosmirror.annual.referral","store":"app_store"}],"items":[{"id":"d663e510","name":"Annual Referral","product_id":"com.iosmirror.annual.referral","store":"app_store"}]},{"id":"74b0f4b2","json":null,"name":"enableFreeTrialOnce","identifier":"enableFreeTrialOnce","default":false,"experiment_id":null,"experiment_name":null,"from_paywall":null,"variation_identifier":null,"variation_name":null,"items_v2":[{"id":"99b0f965","name":"Annual Without Trial","product_id":"com.iosmirror.annual_0_5","store":"app_store"},{"id":"06c48ef5","name":"Annual","product_id":"com.iosmirror.annual","store":"app_store"}],"items":[{"id":"99b0f965","name":"Annual Without Trial","product_id":"com.iosmirror.annual_0_5","store":"app_store"},{"id":"06c48ef5","name":"Annual","product_id":"com.iosmirror.annual","store":"app_store"}]},{"id":"a81ab3e1","json":null,"name":"enableFreeTrialYear","identifier":"enableFreeTrialYear","default":false,"experiment_id":null,"experiment_name":null,"from_paywall":null,"variation_identifier":null,"variation_name":null,"items_v2":[{"id":"99b0f965","name":"Annual Without Trial","product_id":"com.iosmirror.annual_0_5","store":"app_store"},{"id":"790ee64b","name":"Yearly","product_id":"com.iosmirror.yearly","store":"app_store"}],"items":[{"id":"99b0f965","name":"Annual Without Trial","product_id":"com.iosmirror.annual_0_5","store":"app_store"},{"id":"790ee64b","name":"Yearly","product_id":"com.iosmirror.yearly","store":"app_store"}]},{"id":"910018e3","json":null,"name":"control","identifier":"control","default":false,"experiment_id":null,"experiment_name":null,"from_paywall":null,"variation_identifier":null,"variation_name":null,"items_v2":[{"id":"99b0f965","name":"Annual Without Trial","product_id":"com.iosmirror.annual_0_5","store":"app_store"},{"id":"06c48ef5","name":"Annual","product_id":"com.iosmirror.annual","store":"app_store"}],"items":[{"id":"99b0f965","name":"Annual Without Trial","product_id":"com.iosmirror.annual_0_5","store":"app_store"},{"id":"06c48ef5","name":"Annual","product_id":"com.iosmirror.annual","store":"app_store"}]},{"id":"f5d74fe7","json":null,"name":"long","identifier":"long","default":false,"experiment_id":null,"experiment_name":null,"from_paywall":null,"variation_identifier":null,"variation_name":null,"items_v2":[{"id":"06c48ef5","name":"Annual","product_id":"com.iosmirror.annual","store":"app_store"},{"id":"12b11552","name":"Monthly","product_id":"com.iosmirror.monthly","store":"app_store"},{"id":"6ca509d0","name":"Weekly","product_id":"com.iosmirror.weekly","store":"app_store"}],"items":[{"id":"06c48ef5","name":"Annual","product_id":"com.iosmirror.annual","store":"app_store"},{"id":"12b11552","name":"Monthly","product_id":"com.iosmirror.monthly","store":"app_store"},{"id":"6ca509d0","name":"Weekly","product_id":"com.iosmirror.weekly","store":"app_store"}]},{"id":"4396cd61","json":null,"name":"longTrialToggle","identifier":"longTrialToggle","default":true,"experiment_id":null,"experiment_name":null,"from_paywall":null,"variation_identifier":null,"variation_name":null,"items_v2":[{"id":"99b0f965","name":"Annual Without Trial","product_id":"com.iosmirror.annual_0_5","store":"app_store"},{"id":"06c48ef5","name":"Annual","product_id":"com.iosmirror.annual","store":"app_store"}],"items":[{"id":"99b0f965","name":"Annual Without Trial","product_id":"com.iosmirror.annual_0_5","store":"app_store"},{"id":"06c48ef5","name":"Annual","product_id":"com.iosmirror.annual","store":"app_store"}]},{"id":"afbcba26","json":null,"name":"longYearlyLifetime","identifier":"longYearlyLifetime","default":false,"experiment_id":null,"experiment_name":null,"from_paywall":null,"variation_identifier":null,"variation_name":null,"items_v2":[{"id":"99b0f965","name":"Annual Without Trial","product_id":"com.iosmirror.annual_0_5","store":"app_store"},{"id":"f7d92792","name":"Lifetime","product_id":"com.iosmirror.lifetime","store":"app_store"}],"items":[{"id":"99b0f965","name":"Annual Without Trial","product_id":"com.iosmirror.annual_0_5","store":"app_store"},{"id":"f7d92792","name":"Lifetime","product_id":"com.iosmirror.lifetime","store":"app_store"}]},{"id":"44012e34","json":null,"name":"longLifetimeYearly","identifier":"longLifetimeYearly","default":false,"experiment_id":null,"experiment_name":null,"from_paywall":null,"variation_identifier":null,"variation_name":null,"items_v2":[{"id":"f7d92792","name":"Lifetime","product_id":"com.iosmirror.lifetime","store":"app_store"},{"id":"99b0f965","name":"Annual Without Trial","product_id":"com.iosmirror.annual_0_5","store":"app_store"}],"items":[{"id":"f7d92792","name":"Lifetime","product_id":"com.iosmirror.lifetime","store":"app_store"},{"id":"99b0f965","name":"Annual Without Trial","product_id":"com.iosmirror.annual_0_5","store":"app_store"}]},{"id":"502ebb1b","json":null,"name":"longYearly","identifier":"longYearly","default":false,"experiment_id":null,"experiment_name":null,"from_paywall":null,"variation_identifier":null,"variation_name":null,"items_v2":[{"id":"99b0f965","name":"Annual Without Trial","product_id":"com.iosmirror.annual_0_5","store":"app_store"}],"items":[{"id":"99b0f965","name":"Annual Without Trial","product_id":"com.iosmirror.annual_0_5","store":"app_store"}]},{"id":"5109a3c8","json":null,"name":"longYearlyMonthly","identifier":"longYearlyMonthly","default":false,"experiment_id":null,"experiment_name":null,"from_paywall":null,"variation_identifier":null,"variation_name":null,"items_v2":[{"id":"99b0f965","name":"Annual Without Trial","product_id":"com.iosmirror.annual_0_5","store":"app_store"},{"id":"b2fae991","name":"Monthly H Without Trial","product_id":"com.iosmirror.monthly_0_5","store":"app_store"}],"items":[{"id":"99b0f965","name":"Annual Without Trial","product_id":"com.iosmirror.annual_0_5","store":"app_store"},{"id":"b2fae991","name":"Monthly H Without Trial","product_id":"com.iosmirror.monthly_0_5","store":"app_store"}]}],"meta":null},"errors":null}